AUTHORS
ChangeLog
MANIFEST.in
README.md
creds.example.json
openstack-common.conf
secgroups.additional.example.json
secgroups.example.json
setup.cfg
setup.py
tox.ini
bin/stackhelper
python_stackhelper.egg-info/PKG-INFO
python_stackhelper.egg-info/SOURCES.txt
python_stackhelper.egg-info/dependency_links.txt
python_stackhelper.egg-info/entry_points.txt
python_stackhelper.egg-info/requires.txt
python_stackhelper.egg-info/top_level.txt
stackhelper/__init__.py
stackhelper/exceptions.py
stackhelper/shell.py
stackhelper/utils.py
stackhelper/version.py
stackhelper/cli/__init__.py
stackhelper/cli/base.py
stackhelper/cli/credentials.py
stackhelper/cli/secgroup.py
stackhelper/openstack/__init__.py
stackhelper/openstack/common/__init__.py
stackhelper/openstack/common/setup.py
stackhelper/openstack/common/version.py
stackhelper/tests/__init__.py
tools/pip-requires
tools/setup-requires
tools/test-requires