Metadata-Version: 1.1
Name: python-stackhelper
Version: 0.0.6
Summary: OpenStack Helper Utilities
Home-page: https://github.com/moniker-dns/python-stackhelper
Author: Kiall Mac Innes
Author-email: kiall@hp.com
License: UNKNOWN
Platform: UNKNOWN
Classifier: Development Status :: 3 - Alpha
Classifier: License :: OSI Approved :: Apache Software License
Classifier: Operating System :: OS Independent
Classifier: Programming Language :: Python :: 2.6
Classifier: Programming Language :: Python :: 2.7
Classifier: Environment :: Console
Classifier: Environment :: OpenStack
